{
  "asml": {
    "earliest": "2009-07-09",
    "latest": "2026-04-28",
    "count": 4227
  },
  "tokyo_electron": {
    "earliest": "2009-07-16",
    "latest": "2026-04-28",
    "count": 4124
  },
  "lam_research": {
    "earliest": "2009-07-09",
    "latest": "2026-04-28",
    "count": 4227
  },
  "sumco": {
    "earliest": "2009-07-16",
    "latest": "2026-04-28",
    "count": 4124
  },
  "samsung": {
    "earliest": "2009-07-22",
    "latest": "2026-04-29",
    "count": 4129
  },
  "skhynix": {
    "earliest": "2009-07-22",
    "latest": "2026-04-29",
    "count": 4129
  },
  "micron": {
    "earliest": "2009-07-09",
    "latest": "2026-04-28",
    "count": 4227
  },
  "nanya": {
    "earliest": "2009-07-28",
    "latest": "2026-04-29",
    "count": 4100
  },
  "winbond": {
    "earliest": "2009-07-28",
    "latest": "2026-04-29",
    "count": 4100
  },
  "ase": {
    "earliest": "2009-07-28",
    "latest": "2026-04-29",
    "count": 4100
  },
  "powertech": {
    "earliest": "2009-07-28",
    "latest": "2026-04-29",
    "count": 4100
  },
  "ptc": {
    "earliest": "2013-04-19",
    "latest": "2026-04-29",
    "count": 3175,
    "history_complete": true
  },
  "nvidia": {
    "earliest": "2009-07-09",
    "latest": "2026-04-28",
    "count": 4227
  },
  "amd": {
    "earliest": "2009-07-09",
    "latest": "2026-04-28",
    "count": 4227
  },
  "apple": {
    "earliest": "2009-07-09",
    "latest": "2026-04-28",
    "count": 4227
  },
  "aws": {
    "earliest": "2009-07-09",
    "latest": "2026-04-28",
    "count": 4227
  },
  "microsoft": {
    "earliest": "2009-07-09",
    "latest": "2026-04-28",
    "count": 4227
  },
  "google": {
    "earliest": "2009-07-09",
    "latest": "2026-04-28",
    "count": 4227
  },
  "applied_materials": {
    "earliest": "2018-09-10",
    "latest": "2026-04-28",
    "count": 1918
  },
  "kla": {
    "earliest": "2018-09-10",
    "latest": "2026-04-28",
    "count": 1918
  },
  "shin_etsu": {
    "earliest": "2018-09-10",
    "latest": "2026-04-28",
    "count": 1865
  },
  "synopsys": {
    "earliest": "2018-09-10",
    "latest": "2026-04-28",
    "count": 1918
  },
  "cadence": {
    "earliest": "2018-09-10",
    "latest": "2026-04-28",
    "count": 1918
  },
  "arm": {
    "earliest": "2023-09-14",
    "latest": "2026-04-28",
    "count": 657,
    "history_complete": true
  },
  "kioxia": {
    "earliest": "2024-12-18",
    "latest": "2026-04-28",
    "count": 330,
    "history_complete": true
  },
  "western_digital": {
    "earliest": "2018-09-10",
    "latest": "2026-04-28",
    "count": 1918
  },
  "tsmc": {
    "earliest": "2018-09-10",
    "latest": "2026-04-28",
    "count": 1918
  },
  "intel": {
    "earliest": "2018-09-10",
    "latest": "2026-04-28",
    "count": 1918
  },
  "amkor": {
    "earliest": "2018-09-10",
    "latest": "2026-04-28",
    "count": 1918
  },
  "broadcom": {
    "earliest": "2018-09-10",
    "latest": "2026-04-28",
    "count": 1918
  },
  "qualcomm": {
    "earliest": "2018-09-10",
    "latest": "2026-04-28",
    "count": 1918
  },
  "dell": {
    "earliest": "2018-09-10",
    "latest": "2026-04-28",
    "count": 1918
  },
  "hp": {
    "earliest": "2018-09-10",
    "latest": "2026-04-28",
    "count": 1918
  },
  "lenovo": {
    "earliest": "2018-09-07",
    "latest": "2026-04-29",
    "count": 1877
  },
  "supermicro": {
    "earliest": "2018-09-10",
    "latest": "2026-04-28",
    "count": 1918
  },
  "meta": {
    "earliest": "2018-09-10",
    "latest": "2026-04-28",
    "count": 1918
  },
  "oracle": {
    "earliest": "2018-09-10",
    "latest": "2026-04-28",
    "count": 1918
  },
  "screen": {
    "earliest": "2018-12-07",
    "latest": "2026-04-28",
    "count": 1801
  },
  "entegris": {
    "earliest": "2018-12-07",
    "latest": "2026-04-28",
    "count": 1856
  },
  "silicon_motion": {
    "earliest": "2018-12-07",
    "latest": "2026-04-28",
    "count": 1856
  },
  "macronix": {
    "earliest": "2018-12-06",
    "latest": "2026-04-29",
    "count": 1789
  },
  "elite_semi": {
    "earliest": "2018-12-06",
    "latest": "2026-04-29",
    "count": 1789
  },
  "psmc": {
    "earliest": "2020-12-09",
    "latest": "2026-04-29",
    "count": 1303,
    "history_complete": true
  },
  "marvell": {
    "earliest": "2018-12-07",
    "latest": "2026-04-28",
    "count": 1856
  },
  "ti": {
    "earliest": "2018-12-07",
    "latest": "2026-04-28",
    "count": 1856
  },
  "onsemi": {
    "earliest": "2018-12-07",
    "latest": "2026-04-28",
    "count": 1856
  },
  "infineon": {
    "earliest": "2018-12-05",
    "latest": "2026-04-29",
    "count": 1876
  },
  "phison": {
    "earliest": "2018-12-06",
    "latest": "2026-04-29",
    "count": 1789
  },
  "adata": {
    "earliest": "2018-12-06",
    "latest": "2026-04-29",
    "count": 1789
  },
  "innodisk": {
    "earliest": "2018-12-06",
    "latest": "2026-04-29",
    "count": 1789
  },
  "etf_smh": {
    "earliest": "2019-03-07",
    "latest": "2026-04-28",
    "count": 1796
  },
  "etf_soxx": {
    "earliest": "2019-03-07",
    "latest": "2026-04-28",
    "count": 1796
  },
  "etf_soxq": {
    "earliest": "2021-06-11",
    "latest": "2026-04-28",
    "count": 1225,
    "history_complete": true
  }
}