{
  "asml": {
    "earliest": "2024-09-20",
    "latest": "2026-03-13",
    "count": 370
  },
  "tokyo_electron": {
    "earliest": "2024-09-24",
    "latest": "2026-03-13",
    "count": 358
  },
  "lam_research": {
    "earliest": "2024-09-20",
    "latest": "2026-03-13",
    "count": 370
  },
  "sumco": {
    "earliest": "2024-09-24",
    "latest": "2026-03-13",
    "count": 358
  },
  "samsung": {
    "earliest": "2024-09-20",
    "latest": "2026-03-13",
    "count": 356
  },
  "skhynix": {
    "earliest": "2024-09-20",
    "latest": "2026-03-13",
    "count": 356
  },
  "micron": {
    "earliest": "2024-09-20",
    "latest": "2026-03-13",
    "count": 370
  },
  "nanya": {
    "earliest": "2024-09-20",
    "latest": "2026-03-13",
    "count": 354
  },
  "winbond": {
    "earliest": "2024-09-20",
    "latest": "2026-03-13",
    "count": 354
  },
  "ase": {
    "earliest": "2024-09-20",
    "latest": "2026-03-13",
    "count": 354
  },
  "powertech": {
    "earliest": "2024-09-20",
    "latest": "2026-03-13",
    "count": 354
  },
  "ptc": {
    "earliest": "2024-09-20",
    "latest": "2026-03-13",
    "count": 354
  },
  "nvidia": {
    "earliest": "2024-09-20",
    "latest": "2026-03-13",
    "count": 370
  },
  "amd": {
    "earliest": "2024-09-20",
    "latest": "2026-03-13",
    "count": 370
  },
  "apple": {
    "earliest": "2024-09-20",
    "latest": "2026-03-13",
    "count": 370
  },
  "aws": {
    "earliest": "2024-09-20",
    "latest": "2026-03-13",
    "count": 370
  },
  "microsoft": {
    "earliest": "2024-09-20",
    "latest": "2026-03-13",
    "count": 370
  },
  "google": {
    "earliest": "2024-09-20",
    "latest": "2026-03-13",
    "count": 370
  }
}